{"frames": {"image032-5": {"sourceSize": {"h": 375, "w": 500}, "frame": {"h": 375, "w": 500, "x": 0, "y": 375}, "rotated": false, "trimmed": true, "spriteSourceSize": {"x": 0, "y": 0}}, "image032-0": {"sourceSize": {"h": 375, "w": 500}, "frame": {"h": 375, "w": 500, "x": 0, "y": 0}, "rotated": false, "trimmed": true, "spriteSourceSize": {"x": 0, "y": 0}}, "image032-19": {"sourceSize": {"h": 375, "w": 500}, "frame": {"h": 375, "w": 500, "x": 2000, "y": 1125}, "rotated": false, "trimmed": true, "spriteSourceSize": {"x": 0, "y": 0}}, "image032-16": {"sourceSize": {"h": 375, "w": 500}, "frame": {"h": 375, "w": 500, "x": 500, "y": 1125}, "rotated": false, "trimmed": true, "spriteSourceSize": {"x": 0, "y": 0}}, "image032-2": {"sourceSize": {"h": 375, "w": 500}, "frame": {"h": 375, "w": 500, "x": 1000, "y": 0}, "rotated": false, "trimmed": true, "spriteSourceSize": {"x": 0, "y": 0}}, "image032-1": {"sourceSize": {"h": 375, "w": 500}, "frame": {"h": 375, "w": 500, "x": 500, "y": 0}, "rotated": false, "trimmed": true, "spriteSourceSize": {"x": 0, "y": 0}}, "image032-14": {"sourceSize": {"h": 375, "w": 500}, "frame": {"h": 375, "w": 500, "x": 2000, "y": 750}, "rotated": false, "trimmed": true, "spriteSourceSize": {"x": 0, "y": 0}}, "image032-10": {"sourceSize": {"h": 375, "w": 500}, "frame": {"h": 375, "w": 500, "x": 0, "y": 750}, "rotated": false, "trimmed": true, "spriteSourceSize": {"x": 0, "y": 0}}, "image032-8": {"sourceSize": {"h": 375, "w": 500}, "frame": {"h": 375, "w": 500, "x": 1500, "y": 375}, "rotated": false, "trimmed": true, "spriteSourceSize": {"x": 0, "y": 0}}, "image032-6": {"sourceSize": {"h": 375, "w": 500}, "frame": {"h": 375, "w": 500, "x": 500, "y": 375}, "rotated": false, "trimmed": true, "spriteSourceSize": {"x": 0, "y": 0}}, "image032-7": {"sourceSize": {"h": 375, "w": 500}, "frame": {"h": 375, "w": 500, "x": 1000, "y": 375}, "rotated": false, "trimmed": true, "spriteSourceSize": {"x": 0, "y": 0}}, "image032-12": {"sourceSize": {"h": 375, "w": 500}, "frame": {"h": 375, "w": 500, "x": 1000, "y": 750}, "rotated": false, "trimmed": true, "spriteSourceSize": {"x": 0, "y": 0}}, "image032-11": {"sourceSize": {"h": 375, "w": 500}, "frame": {"h": 375, "w": 500, "x": 500, "y": 750}, "rotated": false, "trimmed": true, "spriteSourceSize": {"x": 0, "y": 0}}, "image032-9": {"sourceSize": {"h": 375, "w": 500}, "frame": {"h": 375, "w": 500, "x": 2000, "y": 375}, "rotated": false, "trimmed": true, "spriteSourceSize": {"x": 0, "y": 0}}, "image032-4": {"sourceSize": {"h": 375, "w": 500}, "frame": {"h": 375, "w": 500, "x": 2000, "y": 0}, "rotated": false, "trimmed": true, "spriteSourceSize": {"x": 0, "y": 0}}, "image032-18": {"sourceSize": {"h": 375, "w": 500}, "frame": {"h": 375, "w": 500, "x": 1500, "y": 1125}, "rotated": false, "trimmed": true, "spriteSourceSize": {"x": 0, "y": 0}}, "image032-20": {"sourceSize": {"h": 375, "w": 500}, "frame": {"h": 375, "w": 500, "x": 0, "y": 1500}, "rotated": false, "trimmed": true, "spriteSourceSize": {"x": 0, "y": 0}}, "image032-15": {"sourceSize": {"h": 375, "w": 500}, "frame": {"h": 375, "w": 500, "x": 0, "y": 1125}, "rotated": false, "trimmed": true, "spriteSourceSize": {"x": 0, "y": 0}}, "image032-17": {"sourceSize": {"h": 375, "w": 500}, "frame": {"h": 375, "w": 500, "x": 1000, "y": 1125}, "rotated": false, "trimmed": true, "spriteSourceSize": {"x": 0, "y": 0}}, "image032-13": {"sourceSize": {"h": 375, "w": 500}, "frame": {"h": 375, "w": 500, "x": 1500, "y": 750}, "rotated": false, "trimmed": true, "spriteSourceSize": {"x": 0, "y": 0}}, "image032-21": {"sourceSize": {"h": 375, "w": 500}, "frame": {"h": 375, "w": 500, "x": 500, "y": 1500}, "rotated": false, "trimmed": true, "spriteSourceSize": {"x": 0, "y": 0}}, "image032-3": {"sourceSize": {"h": 375, "w": 500}, "frame": {"h": 375, "w": 500, "x": 1500, "y": 0}, "rotated": false, "trimmed": true, "spriteSourceSize": {"x": 0, "y": 0}}}, "meta": {"image": "image032-22.png", "speed": 0.3, "size": 22}}