{"meta": {"size": 8, "image": "image003-8.gif", "speed": 0.3}, "frames": {"image003-0": {"sourceSize": {"h": 231.66666666666666, "w": 250.0}, "frame": {"y": 0, "x": 0, "h": 231.66666666666666, "w": 250.0}, "trimmed": true, "spriteSourceSize": {"y": 0, "x": 0}, "rotated": false}, "image003-6": {"sourceSize": {"h": 231.66666666666666, "w": 250.0}, "frame": {"y": 463.3333333333333, "x": 0, "h": 231.66666666666666, "w": 250.0}, "trimmed": true, "spriteSourceSize": {"y": 0, "x": 0}, "rotated": false}, "image003-1": {"sourceSize": {"h": 231.66666666666666, "w": 250.0}, "frame": {"y": 0, "x": 250.0, "h": 231.66666666666666, "w": 250.0}, "trimmed": true, "spriteSourceSize": {"y": 0, "x": 0}, "rotated": false}, "image003-4": {"sourceSize": {"h": 231.66666666666666, "w": 250.0}, "frame": {"y": 231.66666666666666, "x": 250.0, "h": 231.66666666666666, "w": 250.0}, "trimmed": true, "spriteSourceSize": {"y": 0, "x": 0}, "rotated": false}, "image003-3": {"sourceSize": {"h": 231.66666666666666, "w": 250.0}, "frame": {"y": 231.66666666666666, "x": 0, "h": 231.66666666666666, "w": 250.0}, "trimmed": true, "spriteSourceSize": {"y": 0, "x": 0}, "rotated": false}, "image003-2": {"sourceSize": {"h": 231.66666666666666, "w": 250.0}, "frame": {"y": 0, "x": 500.0, "h": 231.66666666666666, "w": 250.0}, "trimmed": true, "spriteSourceSize": {"y": 0, "x": 0}, "rotated": false}, "image003-5": {"sourceSize": {"h": 231.66666666666666, "w": 250.0}, "frame": {"y": 231.66666666666666, "x": 500.0, "h": 231.66666666666666, "w": 250.0}, "trimmed": true, "spriteSourceSize": {"y": 0, "x": 0}, "rotated": false}, "image003-7": {"sourceSize": {"h": 231.66666666666666, "w": 250.0}, "frame": {"y": 463.3333333333333, "x": 250.0, "h": 231.66666666666666, "w": 250.0}, "trimmed": true, "spriteSourceSize": {"y": 0, "x": 0}, "rotated": false}}}